_solib_k8/_U_S_Sthird_Uparty_Semp_Cemp-tool___Uthird_Uparty_Semp_Semp-tool_Slib/libemp-tool.so
tf_shell/__init__.py
tf_shell/python/__init__.py
tf_shell/python/_shell_ops.so
tf_shell/python/discrete_gaussian.py
tf_shell/python/shell_context.py
tf_shell/python/shell_key.py
tf_shell/python/shell_ops.py
tf_shell/python/shell_optimizers.py
tf_shell/python/shell_tensor.py
tf_shell_ml/__init__.py
tf_shell_ml/activation.py
tf_shell_ml/conv2d.py
tf_shell_ml/dense.py
tf_shell_ml/dpsgd_model.py
tf_shell_ml/dropout.py
tf_shell_ml/embedding.py
tf_shell_ml/flatten.py
tf_shell_ml/globalaveragepool1d.py
tf_shell_ml/large_tensor.py
tf_shell_ml/max_pool2d.py
tf_shell_ml/postscale_model.py
tf_shell_ml/private_base.py
tf_shell-0.5.0.dist-info/WHEEL
tf_shell-0.5.0.dist-info/METADATA
tf_shell-0.5.0.dist-info/LICENSE
tf_shell-0.5.0.dist-info/README
tf_shell-0.5.0.dist-info/RECORD
