Metadata-Version: 2.1
Name: tf-shell
Author: Google Inc.
Author-email: jchoncholas@gmail.com
Home-page: https://github.com/google/tf-shell
License: Apache 2.0
Summary: TF-Shell: Privacy preserving machine learning with Tensorflow and the SHELL encryption library, built for python 3.11.
Classifier: Topic :: Security :: Cryptography
Classifier: Topic :: Scientific/Engineering :: Artificial Intelligence
Classifier: Topic :: Software Development :: Libraries :: Python Modules
Classifier: Topic :: Scientific/Engineering :: Mathematics
Requires-Python: >=3.9
Requires-Dist: tensorflow[and-cuda]==2.20.0
Version: 0.5.0
